corpkit/__init__.py
corpkit/annotate.py
corpkit/blanknotebook.ipynb
corpkit/build.py
corpkit/completer.py
corpkit/configparse.py
corpkit/configurations.py
corpkit/conll.py
corpkit/constants.py
corpkit/corpus.py
corpkit/cql.py
corpkit/editor.py
corpkit/env.py
corpkit/gui.py
corpkit/inflect.py
corpkit/interrogation.py
corpkit/interrogator.py
corpkit/keys.py
corpkit/layouts.py
corpkit/lazyprop.py
corpkit/make.py
corpkit/model.py
corpkit/multiprocess.py
corpkit/noseinstall.py
corpkit/nosetests.py
corpkit/other.py
corpkit/plotter.py
corpkit/plugins.py
corpkit/process.py
corpkit/stanford-tregex.jar
corpkit/stats.py
corpkit/textprogressbar.py
corpkit/tokenise.py
corpkit/tregex.sh
corpkit/dictionaries/__init__.py
corpkit/dictionaries/bnc.p
corpkit/dictionaries/bnc.py
corpkit/dictionaries/eng_verb_lexicon.p
corpkit/dictionaries/process_types.py
corpkit/dictionaries/queries.py
corpkit/dictionaries/roles.py
corpkit/dictionaries/stopwords.py
corpkit/dictionaries/verblist.py
corpkit/dictionaries/word_transforms.py
corpkit/dictionaries/wordlists.py
corpkit/download/__init__.py
corpkit/download/corenlp.py
corpkit-2.3.8.data/scripts/corpkit
corpkit-2.3.8.data/scripts/corpkit.1
corpkit-2.3.8.data/scripts/new_project
corpkit-2.3.8.data/scripts/parse
corpkit-2.3.8.dist-info/DESCRIPTION.rst
corpkit-2.3.8.dist-info/METADATA
corpkit-2.3.8.dist-info/RECORD
corpkit-2.3.8.dist-info/WHEEL
corpkit-2.3.8.dist-info/dependency_links.txt
corpkit-2.3.8.dist-info/metadata.json
corpkit-2.3.8.dist-info/top_level.txt
