Metadata-Version: 2.0
Name: corpkit
Version: 2.3.8
Summary: A toolkit for working with linguistic corpora
Home-page: http://github.com/interrogator/corpkit
Author: Daniel McDonald
Author-email: mcdonaldd@unimelb.edu.au
License: MIT
Keywords: corpus,linguistics,nlp
Platform: UNKNOWN
Requires-Dist: blessings (>=1.6)
Requires-Dist: chardet
Requires-Dist: joblib
Requires-Dist: matplotlib (>=1.4.3)
Requires-Dist: nltk (>=3.0.0)
Requires-Dist: pandas (>=0.18.1)
Requires-Dist: requests
Requires-Dist: tabview (>=1.4.0)
Requires-Dist: traitlets (>=4.1.0)
